oj/__init__.py
oj/constants.py
oj/problem.py
oj/testcase.py
oj/validators.py
oj_tools-0.0.7.dist-info/METADATA
oj_tools-0.0.7.dist-info/WHEEL
oj_tools-0.0.7.dist-info/top_level.txt
oj_tools-0.0.7.dist-info/RECORD
