Metadata-Version: 2.1
Name: oj-tools
Version: 0.0.7
Summary: tools for Online Judge management
Author-email: hepheir <hepheir@gmail.com>
Project-URL: Homepage, https://https://github.com/hepheir/oj-tools
Project-URL: Issues, https://https://github.com/hepheir/oj-tools/issues
Classifier: Programming Language :: Python :: 3
Classifier: License :: OSI Approved :: MIT License
Classifier: Operating System :: OS Independent
Requires-Python: >=3.9
